usefy/__init__.py
usefy/client.py
usefy/exceptions.py
usefy-2.1.1.dist-info/METADATA
usefy-2.1.1.dist-info/WHEEL
usefy-2.1.1.dist-info/top_level.txt
usefy-2.1.1.dist-info/RECORD
