Metadata-Version: 2.4
Name: usefy
Version: 2.1.1
Summary: Official Python SDK for Usefy - AI Cost Control & Budget Management
Author-email: Usefy <support@usefy.ai>
License: MIT
Project-URL: Homepage, https://usefy.ai
Project-URL: Documentation, https://usefy.ai/docs
Project-URL: Repository, https://github.com/sherlocq61/usefy
Project-URL: Changelog, https://github.com/sherlocq61/usefy/blob/main/CHANGELOG.md
Keywords: ai,openai,anthropic,cost-control,budget,llm,api
Classifier: Development Status :: 4 - Beta
Classifier: Intended Audience :: Developers
Classifier: License :: OSI Approved :: MIT License
Classifier: Programming Language :: Python :: 3
Classifier: Programming Language :: Python :: 3.8
Classifier: Programming Language :: Python :: 3.9
Classifier: Programming Language :: Python :: 3.10
Classifier: Programming Language :: Python :: 3.11
Classifier: Programming Language :: Python :: 3.12
Classifier: Topic :: Software Development :: Libraries :: Python Modules
Requires-Python: >=3.8
Requires-Dist: httpx>=0.24.0
Provides-Extra: dev
Requires-Dist: pytest>=7.0; extra == "dev"
Requires-Dist: pytest-asyncio>=0.21; extra == "dev"
Requires-Dist: black>=23.0; extra == "dev"
Requires-Dist: mypy>=1.0; extra == "dev"
